{"type":"data","nodes":[null,{"type":"data","data":[{"appointees":1,"disclosure_entries":19,"breadcrumb":4},[2],{"id":3,"name":4,"title":5,"slug":6,"pic":7,"in_cabinet":7,"confirmation_status":7,"net_worth_low":8,"net_worth_high":9,"net_worth_plus":10,"holdover":7,"date_of_appointment":11,"title_agency":12,"main_document_id":13,"did":13,"url":14,"file":15,"form_type":16,"form_subtype":17,"agency_name":18},"322","Brian J. Cavanaugh","Associate Director for Homeland Security","cavanaugh-brian-j",null,"602005","1280000","1","2025-01-20","Associate Director for Homeland Security, Office of Management and Budget, Office of Management and Budget","671","https://www.documentcloud.org/documents/26101305-cavanaugh-brian-j-general-278s-new-entrant-278-2025/","Cavanaugh Brian J - General 278s - New Entrant  - 278 - 2025","278","New Entrant Report","Office of Management and Budget",[20,27,33,39,45,51,60,64,67,73,78,83,87,91,94,97,104,106,112,117,123,128],{"description":21,"appointee_id":22,"dsid":23,"endnote":7,"entity_id":24,"id":25,"income_amount":7,"income_category_id":7,"income_type":7,"line_no":10,"metadata":26,"value_category_id":7,"doc_id":13,"doc_url":14,"form_type":16},"American Global Strategies, LLC",322,1,1154,26743,"Senior Vice President, 9/2021 - 1/2025",{"description":28,"appointee_id":22,"dsid":23,"endnote":7,"entity_id":29,"id":30,"income_amount":7,"income_category_id":7,"income_type":7,"line_no":31,"metadata":32,"value_category_id":7,"doc_id":13,"doc_url":14,"form_type":16},"Heritage Foundation",464,26746,"2","Visiting Fellow, 4/2023 - 1/2025",{"description":34,"appointee_id":22,"dsid":23,"endnote":7,"entity_id":35,"id":36,"income_amount":7,"income_category_id":7,"income_type":7,"line_no":37,"metadata":38,"value_category_id":7,"doc_id":13,"doc_url":14,"form_type":16},"FEW Corp",1153,26744,"3","Consultant, 6/2023 - 12/2023",{"description":40,"appointee_id":22,"dsid":23,"endnote":7,"entity_id":41,"id":42,"income_amount":7,"income_category_id":7,"income_type":7,"line_no":43,"metadata":44,"value_category_id":7,"doc_id":13,"doc_url":14,"form_type":16},"Global Energy Security Institute",13523,26745,"4","Consultant, 12/2023 - 5/2024",{"description":46,"appointee_id":22,"dsid":23,"endnote":7,"entity_id":47,"id":48,"income_amount":7,"income_category_id":7,"income_type":7,"line_no":49,"metadata":50,"value_category_id":7,"doc_id":13,"doc_url":14,"form_type":16},"Vandenberg Coalition",2778,26747,"5","Advisory Board Member, 4/2022 - 1/2025",{"description":52,"appointee_id":22,"dsid":53,"endnote":7,"entity_id":54,"id":55,"income_amount":56,"income_category_id":7,"income_type":57,"line_no":10,"metadata":58,"value_category_id":59,"doc_id":13,"doc_url":14,"form_type":16},"Heritage Foundation (Think Tank)",2,13522,26752,75677,"Consulting Fees","",12,{"description":40,"appointee_id":22,"dsid":53,"endnote":7,"entity_id":41,"id":61,"income_amount":62,"income_category_id":7,"income_type":63,"line_no":31,"metadata":58,"value_category_id":59,"doc_id":13,"doc_url":14,"form_type":16},26751,1000,"Publication payment",{"description":46,"appointee_id":22,"dsid":53,"endnote":7,"entity_id":47,"id":65,"income_amount":62,"income_category_id":7,"income_type":66,"line_no":37,"metadata":58,"value_category_id":59,"doc_id":13,"doc_url":14,"form_type":16},26753,"Honorarium for publication",{"description":68,"appointee_id":22,"dsid":53,"endnote":7,"entity_id":69,"id":70,"income_amount":71,"income_category_id":7,"income_type":72,"line_no":43,"metadata":58,"value_category_id":59,"doc_id":13,"doc_url":14,"form_type":16},"American Global Strategies, LLC (Geopolitical and national security advisory firm)",13524,26749,279991,"Salary/Bonus",{"description":74,"appointee_id":22,"dsid":53,"endnote":7,"entity_id":75,"id":76,"income_amount":7,"income_category_id":23,"income_type":58,"line_no":77,"metadata":58,"value_category_id":53,"doc_id":13,"doc_url":14,"form_type":16},"American Global Strategies 401(k) plan",13525,26748,"4.1",{"description":79,"appointee_id":22,"dsid":53,"endnote":7,"entity_id":80,"id":81,"income_amount":7,"income_category_id":23,"income_type":58,"line_no":82,"metadata":58,"value_category_id":53,"doc_id":13,"doc_url":14,"form_type":16},"Cash Balance Plan",13526,26750,"4.2",{"description":21,"appointee_id":22,"dsid":84,"endnote":7,"entity_id":24,"id":85,"income_amount":7,"income_category_id":7,"income_type":7,"line_no":10,"metadata":86,"value_category_id":7,"doc_id":13,"doc_url":14,"form_type":16},3,26754,"I will continue to participate in this defined contribution plan.  The plan sponsor will not make further contributions after my separation. (2023-06-01)",{"description":28,"appointee_id":22,"dsid":88,"endnote":7,"entity_id":29,"id":89,"income_amount":7,"income_category_id":7,"income_type":7,"line_no":10,"metadata":90,"value_category_id":7,"doc_id":13,"doc_url":14,"form_type":16},4,26757,"Services as Visiting Fellow",{"description":34,"appointee_id":22,"dsid":88,"endnote":7,"entity_id":35,"id":92,"income_amount":7,"income_category_id":7,"income_type":7,"line_no":31,"metadata":93,"value_category_id":7,"doc_id":13,"doc_url":14,"form_type":16},26756,"Services as Consultant",{"description":21,"appointee_id":22,"dsid":88,"endnote":7,"entity_id":24,"id":95,"income_amount":7,"income_category_id":7,"income_type":7,"line_no":37,"metadata":96,"value_category_id":7,"doc_id":13,"doc_url":14,"form_type":16},26755,"Services as Senior Vice President",{"description":98,"appointee_id":22,"dsid":99,"endnote":7,"entity_id":100,"id":101,"income_amount":102,"income_category_id":7,"income_type":103,"line_no":10,"metadata":7,"value_category_id":59,"doc_id":13,"doc_url":14,"form_type":16},"Howard County Public Schools System",5,69600,26760,0,"salary",{"description":98,"appointee_id":22,"dsid":99,"endnote":7,"entity_id":100,"id":105,"income_amount":102,"income_category_id":7,"income_type":58,"line_no":31,"metadata":7,"value_category_id":59,"doc_id":13,"doc_url":14,"form_type":16},26759,{"description":107,"appointee_id":22,"dsid":99,"endnote":108,"entity_id":109,"id":110,"income_amount":7,"income_category_id":23,"income_type":58,"line_no":111,"metadata":7,"value_category_id":99,"doc_id":13,"doc_url":14,"form_type":16},"403B","MD Target Date Retirement Plan",11535,26758,"2.1",{"description":113,"appointee_id":22,"dsid":114,"endnote":7,"entity_id":115,"id":116,"income_amount":102,"income_category_id":7,"income_type":58,"line_no":10,"metadata":7,"value_category_id":23,"doc_id":13,"doc_url":14,"form_type":16},"Maryland 529 College Investment Plan",6,31755,26762,{"description":118,"appointee_id":22,"dsid":114,"endnote":7,"entity_id":119,"id":120,"income_amount":102,"income_category_id":7,"income_type":58,"line_no":121,"metadata":7,"value_category_id":122,"doc_id":13,"doc_url":14,"form_type":16},"Portfolio 2030",38516,26763,"1.1",9,{"description":124,"appointee_id":22,"dsid":114,"endnote":7,"entity_id":125,"id":126,"income_amount":102,"income_category_id":7,"income_type":58,"line_no":127,"metadata":7,"value_category_id":122,"doc_id":13,"doc_url":14,"form_type":16},"Equity portfolio",38517,26761,"1.2",{"description":129,"appointee_id":22,"dsid":114,"endnote":7,"entity_id":130,"id":131,"income_amount":7,"income_category_id":23,"income_type":58,"line_no":31,"metadata":7,"value_category_id":88,"doc_id":13,"doc_url":14,"form_type":16},"U.S. Bank #1 (Cash)",13441,26764],"uses":{"params":["slug"]}}]}
