{"type":"data","nodes":[null,{"type":"data","data":[{"appointees":1,"disclosure_entries":37,"breadcrumb":4},[2,18,22,27,32],{"id":3,"name":4,"title":5,"slug":6,"pic":7,"in_cabinet":7,"confirmation_status":7,"net_worth_low":8,"net_worth_high":9,"net_worth_plus":10,"holdover":7,"date_of_appointment":7,"title_agency":11,"main_document_id":12,"did":13,"url":14,"file":15,"form_type":16,"form_subtype":7,"agency_name":17},"573","Ethan Fallang","Deputy Assistant Secretary for Capital Markets","fallang-ethan",null,"6178019","27695000","1","Deputy Assistant Secretary for Capital Markets, Department of the Treasury -- DO","1125","1123","https://www.documentcloud.org/documents/26101772-fallang-ethan-departmental-offices-general-278s-periodic-transaction-278-t-2025-2025-04-04/","Fallang Ethan - Departmental Offices - General 278s - Periodic Transaction  - 278-T - 2025 - 2025-04-04","278 Transaction","Department of the Treasury",{"id":3,"name":4,"title":5,"slug":6,"pic":7,"in_cabinet":7,"confirmation_status":7,"net_worth_low":8,"net_worth_high":9,"net_worth_plus":10,"holdover":7,"date_of_appointment":7,"title_agency":11,"main_document_id":12,"did":19,"url":20,"file":21,"form_type":16,"form_subtype":7,"agency_name":17},"1124","https://www.documentcloud.org/documents/26102000-fallang-ethan-departmental-offices-general-278s-periodic-transaction-278-t-2025-2025-03-28/","Fallang Ethan - Departmental Offices - General 278s - Periodic Transaction  - 278-T - 2025 - 2025-03-28",{"id":3,"name":4,"title":5,"slug":6,"pic":7,"in_cabinet":7,"confirmation_status":7,"net_worth_low":8,"net_worth_high":9,"net_worth_plus":10,"holdover":7,"date_of_appointment":7,"title_agency":11,"main_document_id":12,"did":12,"url":23,"file":24,"form_type":25,"form_subtype":26,"agency_name":17},"https://www.documentcloud.org/documents/26102051-fallang-ethan-departmental-offices-general-278s-new-entrant-278-2025-2025-01-29-14/","Fallang Ethan - Departmental Offices - General 278s - New Entrant  - 278 - 2025 - 2025-01-29 (14)","278","New Entrant Report",{"id":3,"name":4,"title":5,"slug":6,"pic":7,"in_cabinet":7,"confirmation_status":7,"net_worth_low":8,"net_worth_high":9,"net_worth_plus":10,"holdover":7,"date_of_appointment":7,"title_agency":11,"main_document_id":12,"did":28,"url":29,"file":30,"form_type":31,"form_subtype":7,"agency_name":17},"1126","https://www.documentcloud.org/documents/25971612-fallang-ethan-oge-2025-044/","Fallang, Ethan OGE-2025-044","Other Ethics Document",{"id":3,"name":4,"title":5,"slug":6,"pic":7,"in_cabinet":7,"confirmation_status":7,"net_worth_low":8,"net_worth_high":9,"net_worth_plus":10,"holdover":7,"date_of_appointment":7,"title_agency":11,"main_document_id":12,"did":33,"url":34,"file":35,"form_type":36,"form_subtype":7,"agency_name":17},"1127","https://www.documentcloud.org/documents/26102050-fallang-ethan-final-cd/","Fallang Ethan FINAL CD","Certificate of Divestiture",[38,45,52,58,65,71,77,82,88,95,101,108,113,118,124,128,133,139,144,148,152,156,159,162,165,170,175,181,186,189,192,195,200,205,208,210,213,215,218,220,225,230,235,240,245,250,255,260,264,267,272,275,280,282,284,287,290,295,300,304,308,312,317,323,326,331,336,341,346,351,356,361,366,371,376,381,386,391,395,401,406,411,416,421,426,431,436,441,446,451,457,462,467,472,477,482,487,492,495,498,501,504,509,514,519,522,526,531,537,541,546,550,553,556,561,566,569,573,579,584,589,591,597,603,606,608],{"description":39,"appointee_id":40,"dsid":41,"endnote":7,"entity_id":42,"id":43,"income_amount":7,"income_category_id":7,"income_type":7,"line_no":10,"metadata":44,"value_category_id":7,"doc_id":12,"doc_url":23,"form_type":25},"Rumble, Inc.",573,1,2081,37041,"Board Director, 5/2021 - 1/2025",{"description":46,"appointee_id":40,"dsid":41,"endnote":47,"entity_id":48,"id":49,"income_amount":7,"income_category_id":7,"income_type":7,"line_no":50,"metadata":51,"value_category_id":7,"doc_id":12,"doc_url":23,"form_type":25},"Narya Capital Management","Held multiple positions during my tenure. Disclosed last title, held since 2022.",2085,37038,"2","Partner, 2/2020 - 9/2023",{"description":53,"appointee_id":40,"dsid":41,"endnote":7,"entity_id":54,"id":55,"income_amount":7,"income_category_id":7,"income_type":7,"line_no":56,"metadata":57,"value_category_id":7,"doc_id":12,"doc_url":23,"form_type":25},"Viking Insurance, Ltd",75653,37044,"3","Director, 1/2016 - 12/2023",{"description":59,"appointee_id":40,"dsid":41,"endnote":60,"entity_id":61,"id":62,"income_amount":7,"income_category_id":7,"income_type":7,"line_no":63,"metadata":64,"value_category_id":7,"doc_id":12,"doc_url":23,"form_type":25},"Riverview Health Institute","Held multiple positions during my tenure. Disclosed last title, held since 2019.",2082,37040,"4","Board Director, 10/2008 - 1/2025",{"description":66,"appointee_id":40,"dsid":41,"endnote":7,"entity_id":67,"id":68,"income_amount":7,"income_category_id":7,"income_type":7,"line_no":69,"metadata":70,"value_category_id":7,"doc_id":12,"doc_url":23,"form_type":25},"Our Ohio Renewal",75654,37039,"5","Board Director, 4/2017 - 12/2024",{"description":72,"appointee_id":40,"dsid":41,"endnote":7,"entity_id":73,"id":74,"income_amount":7,"income_category_id":7,"income_type":7,"line_no":75,"metadata":76,"value_category_id":7,"doc_id":12,"doc_url":23,"form_type":25},"Family Partnership #1",2083,37035,"6","Consultant, 1/2013 - 1/2025",{"description":78,"appointee_id":40,"dsid":41,"endnote":7,"entity_id":79,"id":80,"income_amount":7,"income_category_id":7,"income_type":7,"line_no":81,"metadata":76,"value_category_id":7,"doc_id":12,"doc_url":23,"form_type":25},"Family Partnership #2",2084,37036,"7",{"description":83,"appointee_id":40,"dsid":41,"endnote":7,"entity_id":84,"id":85,"income_amount":7,"income_category_id":7,"income_type":7,"line_no":86,"metadata":87,"value_category_id":7,"doc_id":12,"doc_url":23,"form_type":25},"Surgery Center of Dayton",75655,37042,"8","Director, 4/2024 - 1/2025",{"description":89,"appointee_id":40,"dsid":41,"endnote":90,"entity_id":91,"id":92,"income_amount":7,"income_category_id":7,"income_type":7,"line_no":93,"metadata":94,"value_category_id":7,"doc_id":12,"doc_url":23,"form_type":25},"Triumph Way Holdings, LLC","Entity has no assets. It was formed but never used. It will remain dormant during my service.",75656,37043,"9","Founder, 9/2024 - Present",{"description":96,"appointee_id":40,"dsid":41,"endnote":90,"entity_id":97,"id":98,"income_amount":7,"income_category_id":7,"income_type":7,"line_no":99,"metadata":100,"value_category_id":7,"doc_id":12,"doc_url":23,"form_type":25},"JDE Enterprise Investments, LLC",75657,37037,"10","Founder, 2/2018 - Present",{"description":102,"appointee_id":40,"dsid":103,"endnote":7,"entity_id":104,"id":105,"income_amount":7,"income_category_id":41,"income_type":106,"line_no":10,"metadata":106,"value_category_id":107,"doc_id":12,"doc_url":23,"form_type":25},"Rumble, Inc., restricted stock units",2,15329,37059,"",9,{"description":39,"appointee_id":40,"dsid":103,"endnote":7,"entity_id":42,"id":109,"income_amount":110,"income_category_id":7,"income_type":111,"line_no":50,"metadata":106,"value_category_id":112,"doc_id":12,"doc_url":23,"form_type":25},37056,162376,"Director Fees",12,{"description":114,"appointee_id":40,"dsid":103,"endnote":7,"entity_id":115,"id":116,"income_amount":117,"income_category_id":7,"income_type":106,"line_no":56,"metadata":106,"value_category_id":112,"doc_id":12,"doc_url":23,"form_type":25},"Roth IRA",7965,37055,0,{"description":119,"appointee_id":40,"dsid":103,"endnote":7,"entity_id":120,"id":121,"income_amount":7,"income_category_id":41,"income_type":106,"line_no":122,"metadata":106,"value_category_id":123,"doc_id":12,"doc_url":23,"form_type":25},"PIMCO StocksPLUS Long Duration Fund Institutional Class Shares (PSLDX)",15330,37052,"3.1",4,{"description":125,"appointee_id":40,"dsid":103,"endnote":7,"entity_id":126,"id":127,"income_amount":117,"income_category_id":7,"income_type":106,"line_no":63,"metadata":106,"value_category_id":112,"doc_id":12,"doc_url":23,"form_type":25},"Riverview Health Institute Defined Contribution Plan",15331,37054,{"description":129,"appointee_id":40,"dsid":103,"endnote":7,"entity_id":130,"id":131,"income_amount":7,"income_category_id":41,"income_type":106,"line_no":132,"metadata":106,"value_category_id":107,"doc_id":12,"doc_url":23,"form_type":25},"Fidelity Total Market Index Fund (FSKAX)",13533,37048,"4.1",{"description":134,"appointee_id":40,"dsid":103,"endnote":7,"entity_id":135,"id":136,"income_amount":7,"income_category_id":41,"income_type":106,"line_no":137,"metadata":106,"value_category_id":138,"doc_id":12,"doc_url":23,"form_type":25},"Fidelity US Bond Index Fund (FXNAX)",8433,37049,"4.2",3,{"description":140,"appointee_id":40,"dsid":103,"endnote":7,"entity_id":141,"id":142,"income_amount":7,"income_category_id":41,"income_type":106,"line_no":143,"metadata":106,"value_category_id":138,"doc_id":12,"doc_url":23,"form_type":25},"Fidelity International Index Fund (FSPSX)",8432,37047,"4.3",{"description":145,"appointee_id":40,"dsid":103,"endnote":7,"entity_id":146,"id":147,"income_amount":7,"income_category_id":41,"income_type":106,"line_no":69,"metadata":106,"value_category_id":107,"doc_id":12,"doc_url":23,"form_type":25},"Rumble, Inc. (RUM)",15332,37057,{"description":102,"appointee_id":40,"dsid":103,"endnote":7,"entity_id":104,"id":149,"income_amount":150,"income_category_id":7,"income_type":151,"line_no":75,"metadata":106,"value_category_id":112,"doc_id":12,"doc_url":23,"form_type":25},37058,145806,"Cash Payout",{"description":59,"appointee_id":40,"dsid":103,"endnote":7,"entity_id":61,"id":153,"income_amount":154,"income_category_id":7,"income_type":155,"line_no":81,"metadata":106,"value_category_id":112,"doc_id":12,"doc_url":23,"form_type":25},37053,97846,"Salary",{"description":72,"appointee_id":40,"dsid":103,"endnote":7,"entity_id":73,"id":157,"income_amount":158,"income_category_id":7,"income_type":155,"line_no":86,"metadata":106,"value_category_id":112,"doc_id":12,"doc_url":23,"form_type":25},37045,68000,{"description":78,"appointee_id":40,"dsid":103,"endnote":7,"entity_id":79,"id":160,"income_amount":161,"income_category_id":7,"income_type":155,"line_no":93,"metadata":106,"value_category_id":112,"doc_id":12,"doc_url":23,"form_type":25},37046,8000,{"description":46,"appointee_id":40,"dsid":103,"endnote":7,"entity_id":48,"id":163,"income_amount":164,"income_category_id":7,"income_type":155,"line_no":99,"metadata":106,"value_category_id":112,"doc_id":12,"doc_url":23,"form_type":25},37050,180512,{"description":166,"appointee_id":40,"dsid":103,"endnote":7,"entity_id":167,"id":168,"income_amount":117,"income_category_id":7,"income_type":106,"line_no":169,"metadata":106,"value_category_id":112,"doc_id":12,"doc_url":23,"form_type":25},"Narya Capital Management Defined Contribution Plan",15333,37051,"11",{"description":171,"appointee_id":40,"dsid":103,"endnote":7,"entity_id":172,"id":173,"income_amount":7,"income_category_id":41,"income_type":106,"line_no":174,"metadata":106,"value_category_id":138,"doc_id":12,"doc_url":23,"form_type":25},"Vanguard Total Stock Market Index Fund Admiral Class Shares (VTSAX)",8139,37062,"11.1",{"description":176,"appointee_id":40,"dsid":103,"endnote":7,"entity_id":177,"id":178,"income_amount":7,"income_category_id":41,"income_type":106,"line_no":179,"metadata":106,"value_category_id":180,"doc_id":12,"doc_url":23,"form_type":25},"Vanguard Total International Stock Index Fund Admiral Shares (VTIAX)",12229,37061,"11.2",5,{"description":182,"appointee_id":40,"dsid":103,"endnote":7,"entity_id":183,"id":184,"income_amount":7,"income_category_id":41,"income_type":106,"line_no":185,"metadata":106,"value_category_id":103,"doc_id":12,"doc_url":23,"form_type":25},"Vanguard Total Bond Market Index Fund Admiral Shares (VBTLX)",11522,37060,"11.3",{"description":39,"appointee_id":40,"dsid":138,"endnote":7,"entity_id":42,"id":187,"income_amount":7,"income_category_id":7,"income_type":7,"line_no":10,"metadata":188,"value_category_id":7,"doc_id":12,"doc_url":23,"form_type":25},37067,"The compensation committee elected to accelerate the vesting of my RSU's which would otherwise be forfeited.  I will also receive partial compensation for my Director's fees which will be $8,500. (2022-09-01)",{"description":59,"appointee_id":40,"dsid":138,"endnote":7,"entity_id":61,"id":190,"income_amount":7,"income_category_id":7,"income_type":7,"line_no":50,"metadata":191,"value_category_id":7,"doc_id":12,"doc_url":23,"form_type":25},37066,"I will continue to participate in this defined contribution plan, but the plan sponsor no longer makes contributions. (2008-10-01)",{"description":46,"appointee_id":40,"dsid":138,"endnote":7,"entity_id":48,"id":193,"income_amount":7,"income_category_id":7,"income_type":7,"line_no":56,"metadata":194,"value_category_id":7,"doc_id":12,"doc_url":23,"form_type":25},37065,"I will continue to participate in this defined contribution plan, but the plan sponsor no longer makes contributions. (2020-02-01)",{"description":196,"appointee_id":40,"dsid":138,"endnote":7,"entity_id":197,"id":198,"income_amount":7,"income_category_id":7,"income_type":7,"line_no":63,"metadata":199,"value_category_id":7,"doc_id":12,"doc_url":23,"form_type":25},"Narya Capital GP I, LP",6265,37063,"Pursuant to my contract, I retain carried interest in Narya Capital GP I, LP, as compensation for services provided from 2/2020 – 9/2023. The percentage was fixed in August 2023. Payment will be made if and when the fund profits from its investments. (2023-08-01)",{"description":201,"appointee_id":40,"dsid":138,"endnote":7,"entity_id":202,"id":203,"income_amount":7,"income_category_id":7,"income_type":7,"line_no":69,"metadata":204,"value_category_id":7,"doc_id":12,"doc_url":23,"form_type":25},"Narya Capital GP II, LP",6266,37064,"Pursuant to my contract, I retain carried interest in Narya Capital GP II, LP, as compensation for services provided from 2/2020 – 9/2023. The percentage was fixed in August 2023. Payment will be made if and when the fund profits from its investments. (2023-08-01)",{"description":39,"appointee_id":40,"dsid":123,"endnote":7,"entity_id":42,"id":206,"income_amount":7,"income_category_id":7,"income_type":7,"line_no":10,"metadata":207,"value_category_id":7,"doc_id":12,"doc_url":23,"form_type":25},37072,"Services as Board Director",{"description":59,"appointee_id":40,"dsid":123,"endnote":7,"entity_id":61,"id":209,"income_amount":7,"income_category_id":7,"income_type":7,"line_no":50,"metadata":207,"value_category_id":7,"doc_id":12,"doc_url":23,"form_type":25},37071,{"description":72,"appointee_id":40,"dsid":123,"endnote":7,"entity_id":73,"id":211,"income_amount":7,"income_category_id":7,"income_type":7,"line_no":56,"metadata":212,"value_category_id":7,"doc_id":12,"doc_url":23,"form_type":25},37068,"Services as Consultant",{"description":78,"appointee_id":40,"dsid":123,"endnote":7,"entity_id":79,"id":214,"income_amount":7,"income_category_id":7,"income_type":7,"line_no":63,"metadata":212,"value_category_id":7,"doc_id":12,"doc_url":23,"form_type":25},37069,{"description":46,"appointee_id":40,"dsid":123,"endnote":7,"entity_id":48,"id":216,"income_amount":7,"income_category_id":7,"income_type":7,"line_no":69,"metadata":217,"value_category_id":7,"doc_id":12,"doc_url":23,"form_type":25},37070,"Services as Partner",{"description":114,"appointee_id":40,"dsid":180,"endnote":7,"entity_id":115,"id":219,"income_amount":117,"income_category_id":7,"income_type":106,"line_no":10,"metadata":7,"value_category_id":112,"doc_id":12,"doc_url":23,"form_type":25},37085,{"description":221,"appointee_id":40,"dsid":180,"endnote":7,"entity_id":222,"id":223,"income_amount":7,"income_category_id":41,"income_type":106,"line_no":224,"metadata":7,"value_category_id":103,"doc_id":12,"doc_url":23,"form_type":25},"SPDR PORTFOLIO S&P 500 ETF (SPLG)",12961,37087,"1.1",{"description":226,"appointee_id":40,"dsid":180,"endnote":7,"entity_id":227,"id":228,"income_amount":7,"income_category_id":41,"income_type":106,"line_no":229,"metadata":7,"value_category_id":180,"doc_id":12,"doc_url":23,"form_type":25},"Vanguard Total Stock Market Index Fund ETF Class Shares (VTI)",8623,37090,"1.2",{"description":231,"appointee_id":40,"dsid":180,"endnote":7,"entity_id":232,"id":233,"income_amount":7,"income_category_id":41,"income_type":106,"line_no":234,"metadata":7,"value_category_id":103,"doc_id":12,"doc_url":23,"form_type":25},"SPDR PORTFOLIO S&P 600 SMALL CAP ETF (SPSM)",18047,37088,"1.3",{"description":236,"appointee_id":40,"dsid":180,"endnote":7,"entity_id":237,"id":238,"income_amount":7,"income_category_id":41,"income_type":106,"line_no":239,"metadata":7,"value_category_id":103,"doc_id":12,"doc_url":23,"form_type":25},"SPDR Portfolio S&P 400 Mid Cap ETF (SPMD)",18048,37086,"1.4",{"description":241,"appointee_id":40,"dsid":180,"endnote":7,"entity_id":242,"id":243,"income_amount":7,"income_category_id":41,"income_type":106,"line_no":244,"metadata":7,"value_category_id":103,"doc_id":12,"doc_url":23,"form_type":25},"VanguardEmerging Markets Stock Index Fund ETF Shares (VWO)",8347,37091,"1.5",{"description":246,"appointee_id":40,"dsid":180,"endnote":7,"entity_id":247,"id":248,"income_amount":7,"income_category_id":41,"income_type":106,"line_no":249,"metadata":7,"value_category_id":180,"doc_id":12,"doc_url":23,"form_type":25},"Vanguard Developed Markets Index Fund ETF Shares (VEA)",7817,37089,"1.6",{"description":251,"appointee_id":40,"dsid":180,"endnote":7,"entity_id":252,"id":253,"income_amount":7,"income_category_id":41,"income_type":106,"line_no":254,"metadata":7,"value_category_id":103,"doc_id":12,"doc_url":23,"form_type":25},"ISHARES CORE US AGGREGATE BOND ETF (AGG)",8250,37081,"1.7",{"description":256,"appointee_id":40,"dsid":180,"endnote":7,"entity_id":257,"id":258,"income_amount":7,"income_category_id":41,"income_type":106,"line_no":259,"metadata":7,"value_category_id":103,"doc_id":12,"doc_url":23,"form_type":25},"iSharesJPMorgan USDEmerging Markets Bond ETF (EMB)",12935,37082,"1.8",{"description":261,"appointee_id":40,"dsid":180,"endnote":7,"entity_id":262,"id":263,"income_amount":117,"income_category_id":7,"income_type":106,"line_no":50,"metadata":7,"value_category_id":112,"doc_id":12,"doc_url":23,"form_type":25},"Kettering Health Network Defined Contribution Plan",70185,37083,{"description":129,"appointee_id":40,"dsid":180,"endnote":7,"entity_id":130,"id":265,"income_amount":7,"income_category_id":41,"income_type":106,"line_no":266,"metadata":7,"value_category_id":180,"doc_id":12,"doc_url":23,"form_type":25},37076,"2.1",{"description":268,"appointee_id":40,"dsid":180,"endnote":7,"entity_id":269,"id":270,"income_amount":7,"income_category_id":41,"income_type":106,"line_no":271,"metadata":7,"value_category_id":180,"doc_id":12,"doc_url":23,"form_type":25},"FidelityGlobal ex US Index Fund (FSGGX)",23537,37080,"2.2",{"description":134,"appointee_id":40,"dsid":180,"endnote":7,"entity_id":135,"id":273,"income_amount":7,"income_category_id":41,"income_type":106,"line_no":274,"metadata":7,"value_category_id":103,"doc_id":12,"doc_url":23,"form_type":25},37078,"2.3",{"description":276,"appointee_id":40,"dsid":180,"endnote":7,"entity_id":277,"id":278,"income_amount":7,"income_category_id":41,"income_type":106,"line_no":279,"metadata":7,"value_category_id":103,"doc_id":12,"doc_url":23,"form_type":25},"Fidelity Small Cap Index Fund (FSSNX)",8440,37075,"2.4",{"description":125,"appointee_id":40,"dsid":180,"endnote":7,"entity_id":126,"id":281,"income_amount":117,"income_category_id":7,"income_type":106,"line_no":56,"metadata":7,"value_category_id":112,"doc_id":12,"doc_url":23,"form_type":25},37084,{"description":129,"appointee_id":40,"dsid":180,"endnote":7,"entity_id":130,"id":283,"income_amount":7,"income_category_id":41,"income_type":106,"line_no":122,"metadata":7,"value_category_id":180,"doc_id":12,"doc_url":23,"form_type":25},37077,{"description":140,"appointee_id":40,"dsid":180,"endnote":7,"entity_id":141,"id":285,"income_amount":7,"income_category_id":41,"income_type":106,"line_no":286,"metadata":7,"value_category_id":103,"doc_id":12,"doc_url":23,"form_type":25},37073,"3.2",{"description":134,"appointee_id":40,"dsid":180,"endnote":7,"entity_id":135,"id":288,"income_amount":7,"income_category_id":41,"income_type":106,"line_no":289,"metadata":7,"value_category_id":103,"doc_id":12,"doc_url":23,"form_type":25},37079,"3.3",{"description":291,"appointee_id":40,"dsid":180,"endnote":7,"entity_id":292,"id":293,"income_amount":7,"income_category_id":41,"income_type":106,"line_no":294,"metadata":7,"value_category_id":103,"doc_id":12,"doc_url":23,"form_type":25},"Fidelity Real Estate Index Fund (FSRNX)",12342,37074,"3.4",{"description":296,"appointee_id":40,"dsid":297,"endnote":7,"entity_id":298,"id":299,"income_amount":7,"income_category_id":41,"income_type":106,"line_no":10,"metadata":7,"value_category_id":103,"doc_id":12,"doc_url":23,"form_type":25},"US Bank #1: HSA (cash)",6,40923,37138,{"description":301,"appointee_id":40,"dsid":297,"endnote":7,"entity_id":302,"id":303,"income_amount":7,"income_category_id":41,"income_type":106,"line_no":50,"metadata":7,"value_category_id":180,"doc_id":12,"doc_url":23,"form_type":25},"Nocterra Brewing, hospitality, Powell, OH",40924,37121,{"description":305,"appointee_id":40,"dsid":297,"endnote":7,"entity_id":306,"id":307,"income_amount":7,"income_category_id":41,"income_type":106,"line_no":56,"metadata":7,"value_category_id":138,"doc_id":12,"doc_url":23,"form_type":25},"Narya Fund I",40925,37120,{"description":309,"appointee_id":40,"dsid":297,"endnote":7,"entity_id":310,"id":311,"income_amount":7,"income_category_id":41,"income_type":106,"line_no":63,"metadata":7,"value_category_id":138,"doc_id":12,"doc_url":23,"form_type":25},"US Bank #2 (cash account)",33877,37139,{"description":313,"appointee_id":40,"dsid":297,"endnote":7,"entity_id":314,"id":315,"income_amount":7,"income_category_id":180,"income_type":316,"line_no":69,"metadata":7,"value_category_id":123,"doc_id":12,"doc_url":23,"form_type":25},"US Bank #3 (cash account)",33878,37140,"Interest",{"description":318,"appointee_id":40,"dsid":297,"endnote":319,"entity_id":320,"id":321,"income_amount":7,"income_category_id":41,"income_type":106,"line_no":75,"metadata":7,"value_category_id":322,"doc_id":12,"doc_url":23,"form_type":25},"Legacy Trust","Owns shares in Family Partnership #1 and #2. Filer has an 23.75% financial interest in Family Partnership #1. Filer has an 11% financial interest in Family Partnership #2.",40926,37117,15,{"description":72,"appointee_id":40,"dsid":297,"endnote":7,"entity_id":73,"id":324,"income_amount":117,"income_category_id":7,"income_type":106,"line_no":325,"metadata":7,"value_category_id":112,"doc_id":12,"doc_url":23,"form_type":25},37107,"6.1",{"description":327,"appointee_id":40,"dsid":297,"endnote":7,"entity_id":328,"id":329,"income_amount":117,"income_category_id":7,"income_type":106,"line_no":330,"metadata":7,"value_category_id":112,"doc_id":12,"doc_url":23,"form_type":25},"Riverview Health Institute, LLC, healthcare, Dayton, OH (value and income not readily ascertainable)",40927,37128,"6.1.1",{"description":332,"appointee_id":40,"dsid":297,"endnote":7,"entity_id":333,"id":334,"income_amount":117,"income_category_id":7,"income_type":106,"line_no":335,"metadata":7,"value_category_id":112,"doc_id":12,"doc_url":23,"form_type":25},"Hendricks Assistance Company, LLC, real estate investments, Middletown, OH (value and income not readily ascertainable)",40928,37116,"6.1.2",{"description":337,"appointee_id":40,"dsid":297,"endnote":7,"entity_id":338,"id":339,"income_amount":117,"income_category_id":7,"income_type":106,"line_no":340,"metadata":7,"value_category_id":112,"doc_id":12,"doc_url":23,"form_type":25},"Buckeye Medical Leasing, LLC, healthcare, Dayton, OH (value and income not readily ascertainable)",40929,37097,"6.1.3",{"description":342,"appointee_id":40,"dsid":297,"endnote":7,"entity_id":343,"id":344,"income_amount":117,"income_category_id":7,"income_type":106,"line_no":345,"metadata":7,"value_category_id":112,"doc_id":12,"doc_url":23,"form_type":25},"Alliance Health Group, LLC, healthcare, Dayton, OH (value and income not readily ascertainable)",40930,37093,"6.1.4",{"description":347,"appointee_id":40,"dsid":297,"endnote":7,"entity_id":348,"id":349,"income_amount":117,"income_category_id":7,"income_type":106,"line_no":350,"metadata":7,"value_category_id":112,"doc_id":12,"doc_url":23,"form_type":25},"Oak Leaf Health Group, LLC, healthcare, Dayton, OH (value and income not readily ascertainable)",40931,37126,"6.1.5",{"description":352,"appointee_id":40,"dsid":297,"endnote":7,"entity_id":353,"id":354,"income_amount":117,"income_category_id":7,"income_type":106,"line_no":355,"metadata":7,"value_category_id":112,"doc_id":12,"doc_url":23,"form_type":25},"Cozumel Leasing, holding company for aircraft and watercraft,  Middletown, OH (value and income not readily ascertainable)",40932,37102,"6.1.6",{"description":357,"appointee_id":40,"dsid":297,"endnote":7,"entity_id":358,"id":359,"income_amount":117,"income_category_id":7,"income_type":106,"line_no":360,"metadata":7,"value_category_id":112,"doc_id":12,"doc_url":23,"form_type":25},"Halo Aviation, holding company for aircraft, Middletown, OH (value and income not readily ascertainable)",40933,37115,"6.1.7",{"description":362,"appointee_id":40,"dsid":297,"endnote":7,"entity_id":363,"id":364,"income_amount":117,"income_category_id":7,"income_type":106,"line_no":365,"metadata":7,"value_category_id":112,"doc_id":12,"doc_url":23,"form_type":25},"Prestige 62, holding company for miscellaneous vehicles, Marco Island, FL (value and income not readily ascertainable)",40934,37127,"6.1.8",{"description":367,"appointee_id":40,"dsid":297,"endnote":7,"entity_id":368,"id":369,"income_amount":117,"income_category_id":7,"income_type":106,"line_no":370,"metadata":7,"value_category_id":112,"doc_id":12,"doc_url":23,"form_type":25},"Utah Power Systems, power generating equipment company, Marco Island, FL (value and income not readily ascertainable)",40935,37141,"6.1.9",{"description":372,"appointee_id":40,"dsid":297,"endnote":7,"entity_id":373,"id":374,"income_amount":117,"income_category_id":7,"income_type":106,"line_no":375,"metadata":7,"value_category_id":112,"doc_id":12,"doc_url":23,"form_type":25},"BROKERAGE ACCOUNT",12432,37095,"6.1.10",{"description":377,"appointee_id":40,"dsid":297,"endnote":7,"entity_id":378,"id":379,"income_amount":7,"income_category_id":297,"income_type":106,"line_no":380,"metadata":7,"value_category_id":138,"doc_id":12,"doc_url":23,"form_type":25},"Vanguard Federal Money Market Fund Investor Shares (VMFXX)",8154,37147,"6.1.10.1",{"description":382,"appointee_id":40,"dsid":297,"endnote":7,"entity_id":383,"id":384,"income_amount":7,"income_category_id":297,"income_type":106,"line_no":385,"metadata":7,"value_category_id":297,"doc_id":12,"doc_url":23,"form_type":25},"Vanguard Ohio Long Term Tax Exempt Investor Class (VOHIX)",40936,37150,"6.1.10.2",{"description":387,"appointee_id":40,"dsid":297,"endnote":7,"entity_id":388,"id":389,"income_amount":7,"income_category_id":297,"income_type":106,"line_no":390,"metadata":7,"value_category_id":297,"doc_id":12,"doc_url":23,"form_type":25},"Vanguard Intermediate Term Tax Exempt Admiral Class (VWIUX)",40937,37149,"6.1.10.3",{"description":226,"appointee_id":40,"dsid":297,"endnote":7,"entity_id":227,"id":392,"income_amount":7,"income_category_id":393,"income_type":106,"line_no":394,"metadata":7,"value_category_id":322,"doc_id":12,"doc_url":23,"form_type":25},37155,8,"6.1.10.4",{"description":396,"appointee_id":40,"dsid":297,"endnote":7,"entity_id":397,"id":398,"income_amount":7,"income_category_id":399,"income_type":106,"line_no":400,"metadata":7,"value_category_id":393,"doc_id":12,"doc_url":23,"form_type":25},"Vanguard Total International Stock Index Fund ETF Shares (VXUS)",8673,37153,7,"6.1.10.5",{"description":402,"appointee_id":40,"dsid":297,"endnote":7,"entity_id":403,"id":404,"income_amount":7,"income_category_id":41,"income_type":106,"line_no":405,"metadata":7,"value_category_id":123,"doc_id":12,"doc_url":23,"form_type":25},"U.S. Bank #1 (Cash)",13441,37135,"6.1.11",{"description":407,"appointee_id":40,"dsid":297,"endnote":7,"entity_id":408,"id":409,"income_amount":7,"income_category_id":41,"income_type":106,"line_no":410,"metadata":7,"value_category_id":107,"doc_id":12,"doc_url":23,"form_type":25},"Note Receivable - PrivCap Chud Mez",40938,37124,"6.1.12",{"description":412,"appointee_id":40,"dsid":297,"endnote":7,"entity_id":413,"id":414,"income_amount":7,"income_category_id":41,"income_type":106,"line_no":415,"metadata":7,"value_category_id":123,"doc_id":12,"doc_url":23,"form_type":25},"Note Receivable - TruTouch Technologies Inc.",40939,37125,"6.1.13",{"description":417,"appointee_id":40,"dsid":297,"endnote":7,"entity_id":418,"id":419,"income_amount":7,"income_category_id":297,"income_type":316,"line_no":420,"metadata":7,"value_category_id":393,"doc_id":12,"doc_url":23,"form_type":25},"Note Receivable - Family Member #1",40940,37122,"6.1.14",{"description":422,"appointee_id":40,"dsid":297,"endnote":7,"entity_id":423,"id":424,"income_amount":7,"income_category_id":180,"income_type":316,"line_no":425,"metadata":7,"value_category_id":107,"doc_id":12,"doc_url":23,"form_type":25},"Note Receivable - Family Member #2",40941,37123,"6.1.15",{"description":427,"appointee_id":40,"dsid":297,"endnote":7,"entity_id":428,"id":429,"income_amount":7,"income_category_id":41,"income_type":106,"line_no":430,"metadata":7,"value_category_id":123,"doc_id":12,"doc_url":23,"form_type":25},"Commercial real estate, Middletown, OH",40942,37101,"6.1.16",{"description":432,"appointee_id":40,"dsid":297,"endnote":7,"entity_id":433,"id":434,"income_amount":7,"income_category_id":41,"income_type":106,"line_no":435,"metadata":7,"value_category_id":123,"doc_id":12,"doc_url":23,"form_type":25},"Farmland, Middletown, OH, leased for cash rent",40943,37111,"6.1.17",{"description":437,"appointee_id":40,"dsid":297,"endnote":7,"entity_id":438,"id":439,"income_amount":7,"income_category_id":41,"income_type":106,"line_no":440,"metadata":7,"value_category_id":297,"doc_id":12,"doc_url":23,"form_type":25},"Farmland and residential rental property, West Alexandria, OH, leased for cash rent",40944,37110,"6.1.18",{"description":442,"appointee_id":40,"dsid":297,"endnote":7,"entity_id":443,"id":444,"income_amount":7,"income_category_id":41,"income_type":106,"line_no":445,"metadata":7,"value_category_id":393,"doc_id":12,"doc_url":23,"form_type":25},"Farmland, Nunda, SD, leased for cash rent",40945,37112,"6.1.19",{"description":447,"appointee_id":40,"dsid":297,"endnote":7,"entity_id":448,"id":449,"income_amount":7,"income_category_id":41,"income_type":106,"line_no":450,"metadata":7,"value_category_id":112,"doc_id":12,"doc_url":23,"form_type":25},"Far Hills Investments, LLP 25% Interest, Real Estate Investment, Dayton, OH (value not readily ascertainable)",40946,37109,"6.1.20",{"description":452,"appointee_id":40,"dsid":297,"endnote":7,"entity_id":453,"id":454,"income_amount":7,"income_category_id":297,"income_type":455,"line_no":456,"metadata":7,"value_category_id":107,"doc_id":12,"doc_url":23,"form_type":25},"The Connor Group Debt Fund XVII, LLC .3246% Interest, real estate investments, Springboro, OH",40947,37133,"Capital Gains","6.1.21",{"description":458,"appointee_id":40,"dsid":297,"endnote":7,"entity_id":459,"id":460,"income_amount":7,"income_category_id":41,"income_type":106,"line_no":461,"metadata":7,"value_category_id":138,"doc_id":12,"doc_url":23,"form_type":25},"Eastham Capital Fund VI, LP .125% Interest, Real Estate Investment, Boca Raton, FL",40948,37105,"6.1.22",{"description":463,"appointee_id":40,"dsid":297,"endnote":7,"entity_id":464,"id":465,"income_amount":7,"income_category_id":41,"income_type":106,"line_no":466,"metadata":7,"value_category_id":138,"doc_id":12,"doc_url":23,"form_type":25},"ROC Venture Group - Grubmarket III, investment in GrubMarket - food delivery, Naples, FL",40949,37130,"6.1.23",{"description":468,"appointee_id":40,"dsid":297,"endnote":7,"entity_id":469,"id":470,"income_amount":7,"income_category_id":41,"income_type":106,"line_no":471,"metadata":7,"value_category_id":297,"doc_id":12,"doc_url":23,"form_type":25},"ROC Fiber Ventures, SPV for investment in HarborLink - Telecom industry, Naples, FL",40950,37129,"6.1.24",{"description":473,"appointee_id":40,"dsid":297,"endnote":7,"entity_id":474,"id":475,"income_amount":7,"income_category_id":41,"income_type":106,"line_no":476,"metadata":7,"value_category_id":123,"doc_id":12,"doc_url":23,"form_type":25},"TruTouch Technologies Inc. Privately Held Stock, Biomedical Sensors, Riverside, CA",40951,37134,"6.1.25",{"description":478,"appointee_id":40,"dsid":297,"endnote":7,"entity_id":479,"id":480,"income_amount":7,"income_category_id":41,"income_type":106,"line_no":481,"metadata":7,"value_category_id":123,"doc_id":12,"doc_url":23,"form_type":25},"Critical Care Diagnostics Privately Held Stock, Medical Devices, San Diego, CA",40952,37103,"6.1.26",{"description":483,"appointee_id":40,"dsid":297,"endnote":7,"entity_id":484,"id":485,"income_amount":7,"income_category_id":41,"income_type":106,"line_no":486,"metadata":7,"value_category_id":393,"doc_id":12,"doc_url":23,"form_type":25},"Gold coins",26895,37113,"6.1.27",{"description":488,"appointee_id":40,"dsid":297,"endnote":7,"entity_id":489,"id":490,"income_amount":7,"income_category_id":41,"income_type":106,"line_no":491,"metadata":7,"value_category_id":180,"doc_id":12,"doc_url":23,"form_type":25},"Silver",40953,37131,"6.1.28",{"description":78,"appointee_id":40,"dsid":297,"endnote":7,"entity_id":79,"id":493,"income_amount":117,"income_category_id":7,"income_type":106,"line_no":494,"metadata":7,"value_category_id":112,"doc_id":12,"doc_url":23,"form_type":25},37108,"6.2",{"description":367,"appointee_id":40,"dsid":297,"endnote":7,"entity_id":368,"id":496,"income_amount":117,"income_category_id":7,"income_type":106,"line_no":497,"metadata":7,"value_category_id":112,"doc_id":12,"doc_url":23,"form_type":25},37142,"6.2.1",{"description":372,"appointee_id":40,"dsid":297,"endnote":7,"entity_id":373,"id":499,"income_amount":117,"income_category_id":7,"income_type":106,"line_no":500,"metadata":7,"value_category_id":112,"doc_id":12,"doc_url":23,"form_type":25},37096,"6.2.2",{"description":377,"appointee_id":40,"dsid":297,"endnote":7,"entity_id":378,"id":502,"income_amount":7,"income_category_id":138,"income_type":106,"line_no":503,"metadata":7,"value_category_id":180,"doc_id":12,"doc_url":23,"form_type":25},37146,"6.2.2.1",{"description":505,"appointee_id":40,"dsid":297,"endnote":7,"entity_id":506,"id":507,"income_amount":7,"income_category_id":123,"income_type":106,"line_no":508,"metadata":7,"value_category_id":138,"doc_id":12,"doc_url":23,"form_type":25},"Vanguard Total Bond Market Index Admiral Class (VBTLX)",40954,37151,"6.2.2.2",{"description":510,"appointee_id":40,"dsid":297,"endnote":7,"entity_id":511,"id":512,"income_amount":7,"income_category_id":180,"income_type":106,"line_no":513,"metadata":7,"value_category_id":297,"doc_id":12,"doc_url":23,"form_type":25},"Vanguard 500 Index Admiral Class (VFIAX)",40955,37144,"6.2.2.3",{"description":515,"appointee_id":40,"dsid":297,"endnote":7,"entity_id":516,"id":517,"income_amount":7,"income_category_id":180,"income_type":106,"line_no":518,"metadata":7,"value_category_id":123,"doc_id":12,"doc_url":23,"form_type":25},"Vanguard Developed Markets Index Fund Admiral Class Shares (VTMGX)",11521,37145,"6.2.2.4",{"description":402,"appointee_id":40,"dsid":297,"endnote":7,"entity_id":403,"id":520,"income_amount":7,"income_category_id":41,"income_type":106,"line_no":521,"metadata":7,"value_category_id":297,"doc_id":12,"doc_url":23,"form_type":25},37136,"6.2.3",{"description":523,"appointee_id":40,"dsid":297,"endnote":7,"entity_id":524,"id":525,"income_amount":117,"income_category_id":7,"income_type":106,"line_no":81,"metadata":7,"value_category_id":112,"doc_id":12,"doc_url":23,"form_type":25},"CoinBase Wallet",31486,37099,{"description":527,"appointee_id":40,"dsid":297,"endnote":7,"entity_id":528,"id":529,"income_amount":7,"income_category_id":41,"income_type":106,"line_no":530,"metadata":7,"value_category_id":123,"doc_id":12,"doc_url":23,"form_type":25},"Bitcoin",13279,37094,"7.1",{"description":532,"appointee_id":40,"dsid":297,"endnote":533,"entity_id":534,"id":535,"income_amount":7,"income_category_id":180,"income_type":316,"line_no":536,"metadata":7,"value_category_id":123,"doc_id":12,"doc_url":23,"form_type":25},"Ethereum","Interest is staking rewards",13529,37106,"7.2",{"description":538,"appointee_id":40,"dsid":297,"endnote":7,"entity_id":539,"id":540,"income_amount":117,"income_category_id":7,"income_type":106,"line_no":86,"metadata":7,"value_category_id":112,"doc_id":12,"doc_url":23,"form_type":25},"College Advantage 529 Accounts",40956,37100,{"description":542,"appointee_id":40,"dsid":297,"endnote":7,"entity_id":543,"id":544,"income_amount":7,"income_category_id":41,"income_type":106,"line_no":545,"metadata":7,"value_category_id":123,"doc_id":12,"doc_url":23,"form_type":25},"Vanguard 500 Index",14540,37143,"8.1",{"description":547,"appointee_id":40,"dsid":297,"endnote":7,"entity_id":548,"id":549,"income_amount":117,"income_category_id":7,"income_type":106,"line_no":93,"metadata":7,"value_category_id":112,"doc_id":12,"doc_url":23,"form_type":25},"U.S. Brokerage account",31831,37137,{"description":176,"appointee_id":40,"dsid":297,"endnote":7,"entity_id":177,"id":551,"income_amount":7,"income_category_id":41,"income_type":106,"line_no":552,"metadata":7,"value_category_id":180,"doc_id":12,"doc_url":23,"form_type":25},37152,"9.1",{"description":171,"appointee_id":40,"dsid":297,"endnote":7,"entity_id":172,"id":554,"income_amount":7,"income_category_id":41,"income_type":106,"line_no":555,"metadata":7,"value_category_id":180,"doc_id":12,"doc_url":23,"form_type":25},37154,"9.2",{"description":557,"appointee_id":40,"dsid":297,"endnote":7,"entity_id":558,"id":559,"income_amount":7,"income_category_id":41,"income_type":106,"line_no":560,"metadata":7,"value_category_id":103,"doc_id":12,"doc_url":23,"form_type":25},"Vanguard Value Index Fund ETF Shares (VTV)",8592,37156,"9.3",{"description":562,"appointee_id":40,"dsid":297,"endnote":7,"entity_id":563,"id":564,"income_amount":7,"income_category_id":41,"income_type":106,"line_no":565,"metadata":7,"value_category_id":103,"doc_id":12,"doc_url":23,"form_type":25},"WisdomTree 90/60 US Balanced Fund (NTSX)",40957,37157,"9.4",{"description":377,"appointee_id":40,"dsid":297,"endnote":7,"entity_id":378,"id":567,"income_amount":7,"income_category_id":41,"income_type":106,"line_no":568,"metadata":7,"value_category_id":41,"doc_id":12,"doc_url":23,"form_type":25},37148,"9.5",{"description":570,"appointee_id":40,"dsid":297,"endnote":7,"entity_id":571,"id":572,"income_amount":117,"income_category_id":7,"income_type":106,"line_no":99,"metadata":7,"value_category_id":112,"doc_id":12,"doc_url":23,"form_type":25},"AcreTrader Investments",40958,37092,{"description":574,"appointee_id":40,"dsid":297,"endnote":575,"entity_id":576,"id":577,"income_amount":7,"income_category_id":41,"income_type":106,"line_no":578,"metadata":7,"value_category_id":138,"doc_id":12,"doc_url":23,"form_type":25},"CVAP Ranch 10, LLC","Fractional ownership of farmland",40959,37104,"10.1",{"description":580,"appointee_id":40,"dsid":297,"endnote":575,"entity_id":581,"id":582,"income_amount":7,"income_category_id":41,"income_type":106,"line_no":583,"metadata":7,"value_category_id":180,"doc_id":12,"doc_url":23,"form_type":25},"C5 Farming LLC",40960,37098,"10.2",{"description":585,"appointee_id":40,"dsid":297,"endnote":575,"entity_id":586,"id":587,"income_amount":7,"income_category_id":41,"income_type":106,"line_no":588,"metadata":7,"value_category_id":180,"doc_id":12,"doc_url":23,"form_type":25},"Tehama Olive Partners LLC",40961,37132,"10.3",{"description":483,"appointee_id":40,"dsid":297,"endnote":7,"entity_id":484,"id":590,"income_amount":7,"income_category_id":41,"income_type":106,"line_no":169,"metadata":7,"value_category_id":138,"doc_id":12,"doc_url":23,"form_type":25},37114,{"description":592,"appointee_id":40,"dsid":297,"endnote":593,"entity_id":594,"id":595,"income_amount":7,"income_category_id":41,"income_type":106,"line_no":596,"metadata":7,"value_category_id":112,"doc_id":12,"doc_url":23,"form_type":25},"Narya Capital GP I, LLC Carried Interest","Value not readily ascertainable - 2% profits interest",40962,37118,"12",{"description":598,"appointee_id":40,"dsid":297,"endnote":599,"entity_id":600,"id":601,"income_amount":7,"income_category_id":41,"income_type":106,"line_no":602,"metadata":7,"value_category_id":112,"doc_id":12,"doc_url":23,"form_type":25},"Narya Capital GP II, LLC Carried Interest","Value not readily ascertainable - 0.5% profits interest",40963,37119,"13",{"description":527,"appointee_id":40,"dsid":399,"endnote":7,"entity_id":528,"id":604,"income_amount":7,"income_category_id":7,"income_type":7,"line_no":10,"metadata":605,"value_category_id":123,"doc_id":19,"doc_url":20,"form_type":16},37033,"Sale, 2025-03-20",{"description":532,"appointee_id":40,"dsid":399,"endnote":7,"entity_id":534,"id":607,"income_amount":7,"income_category_id":7,"income_type":7,"line_no":50,"metadata":605,"value_category_id":123,"doc_id":19,"doc_url":20,"form_type":16},37034,{"description":609,"appointee_id":40,"dsid":393,"endnote":610,"entity_id":611,"id":612,"income_amount":7,"income_category_id":7,"income_type":7,"line_no":10,"metadata":613,"value_category_id":112,"doc_id":12,"doc_url":23,"form_type":25},"Capital One","Paid off monthly",1942,37158,"type: Credit Card, amount: $10,001 - $15,000, year-incurred: 2025, rate: Prime Rate + margin, term: Revolving"],"uses":{"params":["slug"]}}]}
