{"type":"data","nodes":[null,{"type":"data","data":[{"appointees":1,"disclosure_entries":29,"breadcrumb":4},[2,19,24],{"id":3,"name":4,"title":5,"slug":6,"pic":7,"in_cabinet":7,"confirmation_status":8,"net_worth_low":9,"net_worth_high":10,"net_worth_plus":11,"holdover":11,"date_of_appointment":7,"title_agency":12,"main_document_id":13,"did":13,"url":14,"file":15,"form_type":16,"form_subtype":17,"agency_name":18},"1389","Dan Negrea","Representative of the United States of America on the Economic and Social Council of the United Nations, with the rank of Ambassador, and Alternate Representative of the United States of America to the Sessions of the General Assembly of the United Nations","negrea-dan",null,"Confirmed","6250005","30600000","0","Representative of the United States of America on the Economic and Social Council of the United Nations, with the rank of Ambassador, and Alternate Representative of the United States of America to the Sessions of the General Assembly of the United Nations, Department of State","2724","https://www.documentcloud.org/documents/26496955-negrea-dan-final278/","Negrea, Dan  final278","278","Nominee Report","Department of State",{"id":3,"name":4,"title":5,"slug":6,"pic":7,"in_cabinet":7,"confirmation_status":8,"net_worth_low":9,"net_worth_high":10,"net_worth_plus":11,"holdover":11,"date_of_appointment":7,"title_agency":12,"main_document_id":13,"did":20,"url":21,"file":22,"form_type":23,"form_subtype":7,"agency_name":18},"2725","https://www.documentcloud.org/documents/26495449-negrea-dan-final-ea-certification/","Negrea, Dan - Final EA Certification","Ethics Agreement Certification",{"id":3,"name":4,"title":5,"slug":6,"pic":7,"in_cabinet":7,"confirmation_status":8,"net_worth_low":9,"net_worth_high":10,"net_worth_plus":11,"holdover":11,"date_of_appointment":7,"title_agency":12,"main_document_id":13,"did":25,"url":26,"file":27,"form_type":28,"form_subtype":7,"agency_name":18},"2726","https://www.documentcloud.org/documents/26102164-negrea-dan-finalea/","Negrea, Dan  finalEA","Ethics Agreement",[30,38,44,50,57,62,68,73,77,84,86,90,94,97,102,105,110,114,121,125,129,134,137,142],{"description":31,"appointee_id":32,"dsid":33,"endnote":7,"entity_id":34,"id":35,"income_amount":7,"income_category_id":7,"income_type":7,"line_no":36,"metadata":37,"value_category_id":7,"doc_id":13,"doc_url":14,"form_type":16},"Atlantic Council of the United States",1389,1,4303,95969,"1","Senior Director, Freedom and Prosperity Center, 4/2021 - 8/2024",{"description":39,"appointee_id":32,"dsid":33,"endnote":7,"entity_id":40,"id":41,"income_amount":7,"income_category_id":7,"income_type":7,"line_no":42,"metadata":43,"value_category_id":7,"doc_id":13,"doc_url":14,"form_type":16},"Olivier Trouveroy Trust",78077,95971,"2","Trustee, 6/2025 - Present",{"description":45,"appointee_id":32,"dsid":33,"endnote":7,"entity_id":46,"id":47,"income_amount":7,"income_category_id":7,"income_type":7,"line_no":48,"metadata":49,"value_category_id":7,"doc_id":13,"doc_url":14,"form_type":16},"Marcel Fournier Trust",78078,95970,"3","Enforcer, 12/2016 - Present",{"description":31,"appointee_id":32,"dsid":51,"endnote":7,"entity_id":34,"id":52,"income_amount":53,"income_category_id":7,"income_type":54,"line_no":36,"metadata":55,"value_category_id":56,"doc_id":13,"doc_url":14,"form_type":16},2,95973,350542,"Salary","",12,{"description":58,"appointee_id":32,"dsid":51,"endnote":7,"entity_id":59,"id":60,"income_amount":61,"income_category_id":7,"income_type":55,"line_no":42,"metadata":55,"value_category_id":56,"doc_id":13,"doc_url":14,"form_type":16},"IRA",8120,95974,0,{"description":63,"appointee_id":32,"dsid":51,"endnote":7,"entity_id":64,"id":65,"income_amount":7,"income_category_id":33,"income_type":55,"line_no":66,"metadata":55,"value_category_id":67,"doc_id":13,"doc_url":14,"form_type":16},"VANGUARD S&P 500 ETF (VOO)",19070,95975,"2.1",8,{"description":69,"appointee_id":32,"dsid":51,"endnote":7,"entity_id":70,"id":71,"income_amount":7,"income_category_id":33,"income_type":72,"line_no":48,"metadata":55,"value_category_id":56,"doc_id":13,"doc_url":14,"form_type":16},"\"We Win, They Lose, Republican Foreign Policy, and the New Cold War,\" Republic Book Publishers (value not readily ascertainable)",23061,95972,"Rent or Royalties",{"description":31,"appointee_id":32,"dsid":74,"endnote":7,"entity_id":34,"id":75,"income_amount":7,"income_category_id":7,"income_type":7,"line_no":36,"metadata":76,"value_category_id":7,"doc_id":13,"doc_url":14,"form_type":16},4,95976,"Senior Director, Freedom and Prosperity Center",{"description":78,"appointee_id":32,"dsid":79,"endnote":7,"entity_id":80,"id":81,"income_amount":61,"income_category_id":7,"income_type":82,"line_no":36,"metadata":7,"value_category_id":83,"doc_id":13,"doc_url":14,"form_type":16},"Greenwich Garden Design (Landscaping Business)",5,72259,95978,"business income",3,{"description":58,"appointee_id":32,"dsid":79,"endnote":7,"entity_id":59,"id":85,"income_amount":61,"income_category_id":7,"income_type":55,"line_no":42,"metadata":7,"value_category_id":56,"doc_id":13,"doc_url":14,"form_type":16},95979,{"description":87,"appointee_id":32,"dsid":79,"endnote":7,"entity_id":88,"id":89,"income_amount":7,"income_category_id":33,"income_type":55,"line_no":66,"metadata":7,"value_category_id":67,"doc_id":13,"doc_url":14,"form_type":16},"Vanguard 500 Index Fund ETF Shares (VOO)",8416,95981,{"description":91,"appointee_id":32,"dsid":79,"endnote":7,"entity_id":92,"id":93,"income_amount":61,"income_category_id":7,"income_type":55,"line_no":48,"metadata":7,"value_category_id":56,"doc_id":13,"doc_url":14,"form_type":16},"Roth IRA",7965,95980,{"description":87,"appointee_id":32,"dsid":79,"endnote":7,"entity_id":88,"id":95,"income_amount":7,"income_category_id":33,"income_type":55,"line_no":96,"metadata":7,"value_category_id":83,"doc_id":13,"doc_url":14,"form_type":16},95983,"3.1",{"description":98,"appointee_id":32,"dsid":79,"endnote":7,"entity_id":99,"id":100,"income_amount":61,"income_category_id":7,"income_type":55,"line_no":101,"metadata":7,"value_category_id":56,"doc_id":13,"doc_url":14,"form_type":16},"401(K)",13731,95977,"4",{"description":87,"appointee_id":32,"dsid":79,"endnote":7,"entity_id":88,"id":103,"income_amount":7,"income_category_id":33,"income_type":55,"line_no":104,"metadata":7,"value_category_id":67,"doc_id":13,"doc_url":14,"form_type":16},95982,"4.1",{"description":106,"appointee_id":32,"dsid":107,"endnote":7,"entity_id":108,"id":109,"income_amount":61,"income_category_id":7,"income_type":55,"line_no":36,"metadata":7,"value_category_id":56,"doc_id":13,"doc_url":14,"form_type":16},"brokerage account #1",6,25901,95984,{"description":63,"appointee_id":32,"dsid":107,"endnote":7,"entity_id":64,"id":111,"income_amount":7,"income_category_id":67,"income_type":55,"line_no":112,"metadata":7,"value_category_id":113,"doc_id":13,"doc_url":14,"form_type":16},95990,"1.1",15,{"description":115,"appointee_id":32,"dsid":107,"endnote":116,"entity_id":117,"id":118,"income_amount":7,"income_category_id":119,"income_type":120,"line_no":42,"metadata":7,"value_category_id":33,"doc_id":13,"doc_url":14,"form_type":16},"Partnership Stake in Rita's Ice","Sold in 2024.",56537,95987,10,"Capital Gains",{"description":122,"appointee_id":32,"dsid":107,"endnote":7,"entity_id":123,"id":124,"income_amount":7,"income_category_id":33,"income_type":55,"line_no":48,"metadata":7,"value_category_id":74,"doc_id":13,"doc_url":14,"form_type":16},"Global Power Products (electrical equipment) preferred stock",56538,95986,{"description":126,"appointee_id":32,"dsid":107,"endnote":7,"entity_id":127,"id":128,"income_amount":7,"income_category_id":33,"income_type":55,"line_no":101,"metadata":7,"value_category_id":83,"doc_id":13,"doc_url":14,"form_type":16},"U.S. Bank (Cash)",9497,95988,{"description":130,"appointee_id":32,"dsid":107,"endnote":7,"entity_id":131,"id":132,"income_amount":61,"income_category_id":7,"income_type":55,"line_no":133,"metadata":7,"value_category_id":56,"doc_id":13,"doc_url":14,"form_type":16},"brokerage account #2",8415,95985,"5",{"description":87,"appointee_id":32,"dsid":107,"endnote":7,"entity_id":88,"id":135,"income_amount":7,"income_category_id":83,"income_type":55,"line_no":136,"metadata":7,"value_category_id":74,"doc_id":13,"doc_url":14,"form_type":16},95989,"5.1",{"description":138,"appointee_id":32,"dsid":67,"endnote":7,"entity_id":139,"id":140,"income_amount":7,"income_category_id":7,"income_type":7,"line_no":36,"metadata":141,"value_category_id":107,"doc_id":13,"doc_url":14,"form_type":16},"Charles Schwab",2587,95991,"type: Exercised Line of Credit, amount: $500,001 - $1,000,000, year-incurred: 2024, rate: 6.2%, term: Revolving",{"description":143,"appointee_id":32,"dsid":67,"endnote":7,"entity_id":144,"id":145,"income_amount":7,"income_category_id":7,"income_type":7,"line_no":42,"metadata":146,"value_category_id":107,"doc_id":13,"doc_url":14,"form_type":16},"Rocket Mortgage, LLC",74546,95992,"type: Mortgage on Personal Residence, amount: $500,001 - $1,000,000, year-incurred: 2021, rate: 2.4%, term: 30 years"],"uses":{"params":["slug"]}}]}
