{"type":"data","nodes":[null,{"type":"data","data":[{"appointees":1,"disclosure_entries":23,"breadcrumb":4},[2,19],{"id":3,"name":4,"title":5,"slug":6,"pic":7,"in_cabinet":7,"confirmation_status":7,"net_worth_low":8,"net_worth_high":9,"net_worth_plus":10,"holdover":7,"date_of_appointment":11,"title_agency":12,"main_document_id":13,"did":13,"url":14,"file":15,"form_type":16,"form_subtype":17,"agency_name":18},"2027","Andrew J. Whitaker","Deputy Director of Advance","whitaker-andrew-j",null,"15001","50000","0","2025-01-21","Deputy Director of Advance, Department of Justice","3945","https://www.documentcloud.org/documents/26495817-propublica-oge-201-0806-responsive-docs-3-of-3-2025-09-28-12/","ProPublica - OGE 201 - 0806 Responsive Docs (3 of 3) - 2025-09-28-12","278","New Entrant Report","Department of Justice",{"id":3,"name":4,"title":5,"slug":6,"pic":7,"in_cabinet":7,"confirmation_status":7,"net_worth_low":8,"net_worth_high":9,"net_worth_plus":10,"holdover":7,"date_of_appointment":11,"title_agency":12,"main_document_id":13,"did":20,"url":21,"file":22,"form_type":16,"form_subtype":17,"agency_name":18},"3946","https://www.documentcloud.org/documents/26495673-law-robert-t-dhs-278e-5/","Law, Robert T DHS 278e-5",[24,34,40,45,50,55,60,65,70,74,80,84],{"description":25,"appointee_id":26,"dsid":27,"endnote":7,"entity_id":28,"id":29,"income_amount":30,"income_category_id":7,"income_type":31,"line_no":32,"metadata":31,"value_category_id":33,"doc_id":13,"doc_url":14,"form_type":16},"Deloitte",2027,2,40,150673,0,"","1",12,{"description":35,"appointee_id":26,"dsid":27,"endnote":7,"entity_id":36,"id":37,"income_amount":7,"income_category_id":38,"income_type":31,"line_no":39,"metadata":31,"value_category_id":38,"doc_id":13,"doc_url":14,"form_type":16},"Bloomberg US Agg Float Adj Index",24004,150671,1,"1.1",{"description":41,"appointee_id":26,"dsid":27,"endnote":7,"entity_id":42,"id":43,"income_amount":7,"income_category_id":38,"income_type":31,"line_no":44,"metadata":31,"value_category_id":27,"doc_id":13,"doc_url":14,"form_type":16},"Russell 3000 TR USD",24005,150676,"1.2",{"description":46,"appointee_id":26,"dsid":27,"endnote":7,"entity_id":47,"id":48,"income_amount":7,"income_category_id":38,"income_type":31,"line_no":49,"metadata":31,"value_category_id":38,"doc_id":13,"doc_url":14,"form_type":16},"CRSP US Total Market Index",24006,150672,"1.3",{"description":51,"appointee_id":26,"dsid":27,"endnote":7,"entity_id":52,"id":53,"income_amount":7,"income_category_id":38,"income_type":31,"line_no":54,"metadata":31,"value_category_id":27,"doc_id":13,"doc_url":14,"form_type":16},"S&P 500 Index",24007,150677,"1.4",{"description":56,"appointee_id":26,"dsid":27,"endnote":7,"entity_id":57,"id":58,"income_amount":7,"income_category_id":38,"income_type":31,"line_no":59,"metadata":31,"value_category_id":27,"doc_id":13,"doc_url":14,"form_type":16},"FTSE Developed All Cap ex US Index",24008,150674,"1.5",{"description":61,"appointee_id":26,"dsid":27,"endnote":7,"entity_id":62,"id":63,"income_amount":7,"income_category_id":38,"income_type":31,"line_no":64,"metadata":31,"value_category_id":27,"doc_id":13,"doc_url":14,"form_type":16},"FTSE Global All Cap ex US Index",24009,150675,"1.6",{"description":66,"appointee_id":26,"dsid":27,"endnote":7,"entity_id":67,"id":68,"income_amount":7,"income_category_id":38,"income_type":31,"line_no":69,"metadata":31,"value_category_id":27,"doc_id":13,"doc_url":14,"form_type":16},"Spliced International Index",24010,150678,"1.7",{"description":25,"appointee_id":26,"dsid":71,"endnote":7,"entity_id":28,"id":72,"income_amount":7,"income_category_id":7,"income_type":7,"line_no":32,"metadata":73,"value_category_id":7,"doc_id":13,"doc_url":14,"form_type":16},3,150679,"I will not participate in this defined contribution plan after my separation. (2021-07-01)",{"description":75,"appointee_id":26,"dsid":71,"endnote":7,"entity_id":76,"id":77,"income_amount":7,"income_category_id":7,"income_type":7,"line_no":78,"metadata":79,"value_category_id":7,"doc_id":13,"doc_url":14,"form_type":16},"Goliath Political Strategies LLC",4555,150680,"2","Personal LLC for contractual support for clients, and supplemental income. No contracts as of 01/21/2025, and none to report at this time. (2024-01-01)",{"description":75,"appointee_id":26,"dsid":81,"endnote":7,"entity_id":76,"id":82,"income_amount":7,"income_category_id":7,"income_type":7,"line_no":32,"metadata":83,"value_category_id":7,"doc_id":13,"doc_url":14,"form_type":16},4,150681,"Previous presidential campaign and inauguration consulting services.",{"description":85,"appointee_id":26,"dsid":86,"endnote":7,"entity_id":87,"id":88,"income_amount":7,"income_category_id":38,"income_type":89,"line_no":32,"metadata":7,"value_category_id":90,"doc_id":13,"doc_url":14,"form_type":16},"US bank (Cash)",6,18640,150682,"Interest",5],"uses":{"params":["slug"]}}]}
